__init__.py
karlib/__init__.py
karlib/boxify.py
karlib/graphify.py
karlib/matchify.py
karlib/pystack.py
karlib/tablify.py
karlib/timer.py
karlib-0.0.3.dist-info/LICENSE
karlib-0.0.3.dist-info/METADATA
karlib-0.0.3.dist-info/WHEEL
karlib-0.0.3.dist-info/top_level.txt
karlib-0.0.3.dist-info/RECORD
