Metadata-Version: 2.1
Name: karlib
Version: 0.0.3
Summary: Kar's library of utilities
Home-page: https://github.com/kartarake/KarLib.git
Author: kartarake
Author-email: kar.prahveen@gmail.com
License: MIT
License-File: LICENSE
